mxdev/__init__.py
mxdev/_version.py
mxdev/config.py
mxdev/entry_points.py
mxdev/hooks.py
mxdev/including.py
mxdev/logging.py
mxdev/main.py
mxdev/processing.py
mxdev/state.py
mxdev/vcs/bazaar.py
mxdev/vcs/common.py
mxdev/vcs/darcs.py
mxdev/vcs/filesystem.py
mxdev/vcs/git.py
mxdev/vcs/gitsvn.py
mxdev/vcs/mercurial.py
mxdev/vcs/svn.py
mxdev-5.1.0.dist-info/METADATA
mxdev-5.1.0.dist-info/WHEEL
mxdev-5.1.0.dist-info/entry_points.txt
mxdev-5.1.0.dist-info/licenses/LICENSE.md
mxdev-5.1.0.dist-info/RECORD
