Metadata-Version: 2.4
Name: mxdev
Version: 5.1.0
Summary: Enable to work with Python projects containing lots of packages, of which you only want to develop some.
Project-URL: Homepage, https://github.com/mxstack/mxdev
Project-URL: Bug Reports, https://github.com/mxstack/mxdev/issues
Project-URL: Source, https://github.com/mxstack/mxdev/
Author-email: MX Stack Developers <dev@bluedynamics.com>
License: BSD 2-Clause License
License-File: LICENSE.md
Keywords: development,git,pip,vcs
Classifier: Development Status :: 5 - Production/Stable
Classifier: Intended Audience :: Developers
Classifier: License :: OSI Approved :: BSD License
Classifier: Operating System :: OS Independent
Classifier: Programming Language :: Python
Classifier: Programming Language :: Python :: 3.10
Classifier: Programming Language :: Python :: 3.11
Classifier: Programming Language :: Python :: 3.12
Classifier: Programming Language :: Python :: 3.13
Classifier: Programming Language :: Python :: 3.14
Classifier: Topic :: Software Development :: Build Tools
Requires-Python: >=3.10
Requires-Dist: packaging
Provides-Extra: mypy
Provides-Extra: test
Requires-Dist: coverage[toml]; extra == 'test'
Requires-Dist: httpretty; extra == 'test'
Requires-Dist: pytest; extra == 'test'
Requires-Dist: pytest-cov; extra == 'test'
Requires-Dist: pytest-mock; extra == 'test'
